[
  {
    "No": "31",
    "Result": "Loss",
    "Record": "30–1",
    "Opponent": "Canelo Álvarez",
    "Type": "RTD",
    "Round_Time": "8 (12), 3:00",
    "Date": "8 May 2021",
    "Location": "AT&T Stadium, Arlington, Texas, US",
    "Notes": "Lost WBO super-middleweight title;For WBA (Super), WBC, and The Ring super-middleweight titles"
  },
  {
    "No": "30",
    "Result": "Win",
    "Record": "30–0",
    "Opponent": "Martin Murray",
    "Type": "UD",
    "Round_Time": "12",
    "Date": "4 Dec 2020",
    "Location": "The SSE Arena, London, England",
    "Notes": "Retained WBO super-middleweight title"
  },
  {
    "No": "29",
    "Result": "Win",
    "Record": "29–0",
    "Opponent": "Marcelo Esteban Coceres",
    "Type": "KO",
    "Round_Time": "11 (12), 1:59",
    "Date": "9 Nov 2019",
    "Location": "Staples Center, Los Angeles, California, US",
    "Notes": "Retained WBO super-middleweight title"
  },
  {
    "No": "28",
    "Result": "Win",
    "Record": "28–0",
    "Opponent": "Shefat Isufi",
    "Type": "UD",
    "Round_Time": "12",
    "Date": "18 May 2019",
    "Location": "Lamex Stadium, Stevenage, England",
    "Notes": "Won vacant WBO super-middleweight title"
  },
  {
    "No": "27",
    "Result": "Win",
    "Record": "27–0",
    "Opponent": "Charles Adamu",
    "Type": "RTD",
    "Round_Time": "4 (8), 3:00",
    "Date": "22 Dec 2018",
    "Location": "Manchester Arena, Manchester, England",
    "Notes": ""
  },
  {
    "No": "26",
    "Result": "Win",
    "Record": "26–0",
    "Opponent": "David Lemieux",
    "Type": "UD",
    "Round_Time": "12",
    "Date": "16 Dec 2017",
    "Location": "Place Bell, Laval, Quebec, Canada",
    "Notes": "Retained WBO middleweight title"
  },
  {
    "No": "25",
    "Result": "Win",
    "Record": "25–0",
    "Opponent": "Willie Monroe Jr.",
    "Type": "UD",
    "Round_Time": "12",
    "Date": "16 Sep 2017",
    "Location": "Copper Box Arena, London, England",
    "Notes": "Retained WBO middleweight title"
  },
  {
    "No": "24",
    "Result": "Win",
    "Record": "24–0",
    "Opponent": "Artur Akavov",
    "Type": "UD",
    "Round_Time": "12",
    "Date": "3 Dec 2016",
    "Location": "Lagoon Leisure Centre, Paisley, Scotland",
    "Notes": "Retained WBO middleweight title"
  },
  {
    "No": "23",
    "Result": "Win",
    "Record": "23–0",
    "Opponent": "Andy Lee",
    "Type": "MD",
    "Round_Time": "12",
    "Date": "19 Dec 2015",
    "Location": "Manchester Arena, Manchester, England",
    "Notes": "Won WBO middleweight title"
  },
  {
    "No": "22",
    "Result": "Win",
    "Record": "22–0",
    "Opponent": "Yoann Bloyer",
    "Type": "TKO",
    "Round_Time": "4 (12), 0:53",
    "Date": "24 Jul 2015",
    "Location": "The SSE Arena, London, England",
    "Notes": ""
  },
  {
    "No": "21",
    "Result": "Win",
    "Record": "21–0",
    "Opponent": "Chris Eubank Jr.",
    "Type": "SD",
    "Round_Time": "12",
    "Date": "29 Nov 2014",
    "Location": "ExCeL, London, England",
    "Notes": "Retained European, British, and Commonwealth middleweight titles"
  },
  {
    "No": "20",
    "Result": "Win",
    "Record": "20–0",
    "Opponent": "Emanuele Blandamura",
    "Type": "KO",
    "Round_Time": "8 (12), 2:58",
    "Date": "26 Jul 2014",
    "Location": "Manchester Arena, Manchester, England",
    "Notes": "Won vacant European middleweight title"
  },
  {
    "No": "19",
    "Result": "Win",
    "Record": "19–0",
    "Opponent": "John Ryder",
    "Type": "UD",
    "Round_Time": "12",
    "Date": "21 Sep 2013",
    "Location": "Copper Box Arena, London, England",
    "Notes": "Retained British and Commonwealth middleweight titles"
  },
  {
    "No": "18",
    "Result": "Win",
    "Record": "18–0",
    "Opponent": "Gary O'Sullivan",
    "Type": "UD",
    "Round_Time": "12",
    "Date": "20 Jul 2013",
    "Location": "Wembley Arena, London, England",
    "Notes": "Won WBO International middleweight title"
  },
  {
    "No": "17",
    "Result": "Win",
    "Record": "17–0",
    "Opponent": "Matthew Hall",
    "Type": "UD",
    "Round_Time": "12",
    "Date": "21 Mar 2013",
    "Location": "York Hall, London, England",
    "Notes": "Retained British and Commonwealth middleweight titles"
  },
  {
    "No": "16",
    "Result": "Win",
    "Record": "16–0",
    "Opponent": "Nick Blackwell",
    "Type": "UD",
    "Round_Time": "12",
    "Date": "15 Dec 2012",
    "Location": "ExCeL, London, England",
    "Notes": "Retained Commonwealth middleweight title;Won vacant British middleweight title"
  },
  {
    "No": "15",
    "Result": "Win",
    "Record": "15–0",
    "Opponent": "Jarrod Fletcher",
    "Type": "TKO",
    "Round_Time": "2 (12), 2:42",
    "Date": "14 Sep 2012",
    "Location": "York Hall, London, England",
    "Notes": "Retained Commonwealth middleweight title"
  },
  {
    "No": "14",
    "Result": "Win",
    "Record": "14–0",
    "Opponent": "Bradley Pryce",
    "Type": "UD",
    "Round_Time": "12",
    "Date": "1 Jun 2012",
    "Location": "York Hall, London, England",
    "Notes": "Retained Commonwealth middleweight title"
  },
  {
    "No": "13",
    "Result": "Win",
    "Record": "13–0",
    "Opponent": "Tony Hill",
    "Type": "TKO",
    "Round_Time": "1 (10), 0:30",
    "Date": "28 Apr 2012",
    "Location": "Royal Albert Hall, London, England",
    "Notes": "Won vacant Commonwealth middleweight title"
  },
  {
    "No": "12",
    "Result": "Win",
    "Record": "12–0",
    "Opponent": "Tommy Tolan",
    "Type": "TKO",
    "Round_Time": "1 (8), 1:07",
    "Date": "14 Dec 2011",
    "Location": "York Hall, London, England",
    "Notes": ""
  },
  {
    "No": "11",
    "Result": "Win",
    "Record": "11–0",
    "Opponent": "Gary Boulden",
    "Type": "PTS",
    "Round_Time": "10",
    "Date": "5 Nov 2011",
    "Location": "Wembley Arena, London, England",
    "Notes": "Won Southern Area middleweight title"
  },
  {
    "No": "10",
    "Result": "Win",
    "Record": "10–0",
    "Opponent": "Norbert Szekeres",
    "Type": "TKO",
    "Round_Time": "1 (8), 2:51",
    "Date": "15 Oct 2011",
    "Location": "Echo Arena, Liverpool, England",
    "Notes": ""
  },
  {
    "No": "9",
    "Result": "Win",
    "Record": "9–0",
    "Opponent": "Kevin Hammond",
    "Type": "TKO",
    "Round_Time": "2 (8), 3:00",
    "Date": "21 May 2011",
    "Location": "The O2 Arena, London, England",
    "Notes": ""
  },
  {
    "No": "8",
    "Result": "Win",
    "Record": "8–0",
    "Opponent": "Turgay Uzun",
    "Type": "RTD",
    "Round_Time": "2 (8), 3:00",
    "Date": "2 Apr 2011",
    "Location": "York Hall, London, England",
    "Notes": ""
  },
  {
    "No": "7",
    "Result": "Win",
    "Record": "7–0",
    "Opponent": "Tony Randell",
    "Type": "TKO",
    "Round_Time": "2 (6), 0:39",
    "Date": "11 Dec 2010",
    "Location": "Echo Arena, Liverpool, England",
    "Notes": ""
  },
  {
    "No": "6",
    "Result": "Win",
    "Record": "6–0",
    "Opponent": "Andy Butlin",
    "Type": "PTS",
    "Round_Time": "6",
    "Date": "15 May 2010",
    "Location": "Boleyn Ground, London, England",
    "Notes": ""
  },
  {
    "No": "5",
    "Result": "Win",
    "Record": "5–0",
    "Opponent": "Lee Noble",
    "Type": "PTS",
    "Round_Time": "6",
    "Date": "5 Dec 2009",
    "Location": "Metro Radio Arena, Newcastle, England",
    "Notes": ""
  },
  {
    "No": "4",
    "Result": "Win",
    "Record": "4–0",
    "Opponent": "Alex Spitko",
    "Type": "PTS",
    "Round_Time": "4",
    "Date": "9 Oct 2009",
    "Location": "York Hall, London, England",
    "Notes": ""
  },
  {
    "No": "3",
    "Result": "Win",
    "Record": "3–0",
    "Opponent": "Matt Scriven",
    "Type": "TKO",
    "Round_Time": "2 (4), 1:21",
    "Date": "18 Jul 2009",
    "Location": "MEN Arena, Manchester, England",
    "Notes": ""
  },
  {
    "No": "2",
    "Result": "Win",
    "Record": "2–0",
    "Opponent": "Ronny Gabel",
    "Type": "TKO",
    "Round_Time": "2 (4), 1:16",
    "Date": "15 May 2009",
    "Location": "Odyssey Arena, Belfast, Northern Ireland",
    "Notes": ""
  },
  {
    "No": "1",
    "Result": "Win",
    "Record": "1–0",
    "Opponent": "Attila Molnar",
    "Type": "TKO",
    "Round_Time": "2 (4), 1:47",
    "Date": "28 Feb 2009",
    "Location": "National Indoor Arena, Birmingham, England",
    "Notes": ""
  }
]
