{"name":"Javier Castillejo","imageUrl":"//upload.wikimedia.org/wikipedia/commons/thumb/9/99/Javier_Castillejo.jpg/220px-Javier_Castillejo.jpg","Real name":"Francisco Javier Castillejo Rodríguez","Nickname(s)":"El Lince de Parla(\"The Lynx of Parla\")","Weight(s)":"\nWelterweight\nLight-middleweight\nMiddleweight\n","Height":"5 ft 11 in (180 cm)[1]","Reach":"70 in (178 cm)[1]","Nationality":"Spanish","Born":" (1968-03-22) 22 March 1968 (age 54)Parla, Madrid, Spain","Stance":"Orthodox","Total fights":"72","Wins":"62","Wins by KO":"43","Losses":"8","Draws":"1","No contests":"1","record":[{"No":"72\n","Result":"Draw\n","Record":"62–8–1 (1)\n","Opponent":"Pablo Navascues\n","Type":"MD\n","Round_Time":"10\n","Date":"4 Apr 2009\n","Location":"La Cubierta, Leganés, Spain\n","Notes":"\n"},{"No":"71\n","Result":"Loss\n","Record":"62–8 (1)\n","Opponent":"Sebastian Sylvester\n","Type":"KO\n","Round_Time":"12 (12), 1:53\n","Date":"12 Apr 2008\n","Location":"Jahnsportforum, Neubrandenburg, Germany\n","Notes":"For European middleweight title\n"},{"No":"70\n","Result":"Win\n","Record":"62–7 (1)\n","Opponent":"Mariano Natalio Carrera\n","Type":"KO\n","Round_Time":"6 (12), 2:14\n","Date":"13 Nov 2007\n","Location":"Hohenstaufenhalle, Göppingen, Germany\n","Notes":"\n"},{"No":"69\n","Result":"Loss\n","Record":"61–7 (1)\n","Opponent":"Felix Sturm\n","Type":"UD\n","Round_Time":"12\n","Date":"28 Apr 2007\n","Location":"König Pilsener Arena, Oberhausen, Germany\n","Notes":"Lost WBA middleweight title\n"},{"No":"68\n","Result":"NC\n","Record":"61–6 (1)\n","Opponent":"Mariano Natalio Carrera\n","Type":"TKO\n","Round_Time":"11 (12), 1:53\n","Date":"2 Dec 2006\n","Location":"Estrel Hotel, Berlin, Germany\n","Notes":"WBA (Regular) middleweight title at stake;Originally a TKO win for Carrera, later ruled an NC after he failed a drug test\n"},{"No":"67\n","Result":"Win\n","Record":"61–6\n","Opponent":"Felix Sturm\n","Type":"TKO\n","Round_Time":"10 (12), 2:47\n","Date":"15 Jul 2006\n","Location":"Color Line Arena, Hamburg, Germany\n","Notes":"Won WBA (Regular) middleweight title\n"},{"No":"66\n","Result":"Win\n","Record":"60–6\n","Opponent":"Luis Carmona\n","Type":"TKO\n","Round_Time":"2 (10)\n","Date":"3 Feb 2006\n","Location":"Santa Cruz de Tenerife, Spain\n","Notes":"\n"},{"No":"65\n","Result":"Win\n","Record":"59–6\n","Opponent":"Presente Brito\n","Type":"PTS\n","Round_Time":"8\n","Date":"4 Nov 2005\n","Location":"La Cubierta, Leganés, Spain\n","Notes":"\n"},{"No":"64\n","Result":"Loss\n","Record":"58–6\n","Opponent":"Fernando Vargas\n","Type":"UD\n","Round_Time":"10\n","Date":"20 Aug 2005\n","Location":"Allstate Arena, Rosemont, Illinois, US\n","Notes":"\n"},{"No":"63\n","Result":"Win\n","Record":"58–5\n","Opponent":"Enrique Campos\n","Type":"TKO\n","Round_Time":"5 (8)\n","Date":"11 Jun 2004\n","Location":"La Cubierta, Leganés, Spain\n","Notes":"\n"},{"No":"62\n","Result":"Win\n","Record":"57–5\n","Opponent":"Genaro Rios\n","Type":"TKO\n","Round_Time":"3 (10)\n","Date":"16 Apr 2004\n","Location":"La Cubierta, Leganés, Spain\n","Notes":"\n"},{"No":"61\n","Result":"Win\n","Record":"56–5\n","Opponent":"Ignacio Solar\n","Type":"TKO\n","Round_Time":"2 (10), 2:26\n","Date":"12 Sep 2003\n","Location":"La Cubierta, Leganés, Spain\n","Notes":"\n"},{"No":"60\n","Result":"Win\n","Record":"55–5\n","Opponent":"Diego Castillo\n","Type":"TKO\n","Round_Time":"1 (12)\n","Date":"9 May 2003\n","Location":"La Cubierta, Leganés, Spain\n","Notes":"Retained WBC interim light-middleweight title\n"},{"No":"59\n","Result":"Win\n","Record":"54–5\n","Opponent":"Roman Karmazin\n","Type":"UD\n","Round_Time":"12\n","Date":"12 Jul 2002\n","Location":"Club Polideportivo, Parla, Spain\n","Notes":"Won vacant WBC interim light-middleweight title\n"},{"No":"58\n","Result":"Win\n","Record":"53–5\n","Opponent":"Pierre Moreno\n","Type":"TKO\n","Round_Time":"7 (10)\n","Date":"26 Apr 2002\n","Location":"Palau Blaugrana, Barcelona, Spain\n","Notes":"Retained European Union light-middleweight title\n"},{"No":"57\n","Result":"Win\n","Record":"52–5\n","Opponent":"Xavier Moya\n","Type":"TKO\n","Round_Time":"5 (10)\n","Date":"11 Jan 2002\n","Location":"Palau Blaugrana, Barcelona, Spain\n","Notes":"Won inaugural European Union light-middleweight title\n"},{"No":"56\n","Result":"Loss\n","Record":"51–5\n","Opponent":"Oscar De La Hoya\n","Type":"UD\n","Round_Time":"12\n","Date":"23 Jun 2001\n","Location":"MGM Grand Garden Arena, Paradise, Nevada, US\n","Notes":"Lost WBC light-middleweight title\n"},{"No":"55\n","Result":"Win\n","Record":"51–4\n","Opponent":"Javier Martinez Rodriguez\n","Type":"TKO\n","Round_Time":"4 (12), 1:43\n","Date":"21 Oct 2000\n","Location":"Salon 21, Mexico City, Mexico\n","Notes":"Retained WBC light-middleweight title\n"},{"No":"54\n","Result":"Win\n","Record":"50–4\n","Opponent":"Tony Marshall\n","Type":"UD\n","Round_Time":"12\n","Date":"21 Jul 2000\n","Location":"La Cubierta, Leganés, Spain\n","Notes":"Retained WBC light-middleweight title\n"},{"No":"53\n","Result":"Win\n","Record":"49–4\n","Opponent":"Juan Rondon\n","Type":"TKO\n","Round_Time":"3 (10)\n","Date":"14 Apr 2000\n","Location":"La Cubierta, Leganés, Spain\n","Notes":"\n"},{"No":"52\n","Result":"Win\n","Record":"48–4\n","Opponent":"Mohamed Boualleg\n","Type":"KO\n","Round_Time":"8 (10)\n","Date":"17 Mar 2000\n","Location":"Ciudad Real, Spain\n","Notes":"\n"},{"No":"51\n","Result":"Win\n","Record":"47–4\n","Opponent":"Michael Rask\n","Type":"TKO\n","Round_Time":"7 (12), 1:41\n","Date":"17 Dec 1999\n","Location":"La Cubierta, Leganés, Spain\n","Notes":"Retained WBC light-middleweight title\n"},{"No":"50\n","Result":"Win\n","Record":"46–4\n","Opponent":"Paolo Roberto\n","Type":"TKO\n","Round_Time":"7 (12), 1:47\n","Date":"10 Sep 1999\n","Location":"La Cubierta, Leganés, Spain\n","Notes":"Retained WBC light-middleweight title\n"},{"No":"49\n","Result":"Win\n","Record":"45–4\n","Opponent":"Humberto Aranda\n","Type":"TKO\n","Round_Time":"4 (12), 2:52\n","Date":"14 May 1999\n","Location":"Pabellón Europa, Leganés, Spain\n","Notes":"Retained WBC light-middleweight title\n"},{"No":"48\n","Result":"Win\n","Record":"44–4\n","Opponent":"Keith Mullings\n","Type":"MD\n","Round_Time":"12\n","Date":"29 Jan 1999\n","Location":"La Cubierta, Leganés, Spain\n","Notes":"Won WBC light-middleweight title\n"},{"No":"47\n","Result":"Win\n","Record":"43–4\n","Opponent":"Cristinel Acatrinei\n","Type":"TKO\n","Round_Time":"2 (8)\n","Date":"16 Oct 1998\n","Location":"La Cubierta, Leganés, Spain\n","Notes":"\n"},{"No":"46\n","Result":"Win\n","Record":"42–4\n","Opponent":"Ahmet Dottuev\n","Type":"TKO\n","Round_Time":"12 (12), 1:38\n","Date":"2 Jul 1998\n","Location":"Corn Exchange, Ipswich, England\n","Notes":"Won vacant European light-middleweight title\n"},{"No":"45\n","Result":"Win\n","Record":"41–4\n","Opponent":"Fernando Jose Riera\n","Type":"PTS\n","Round_Time":"10\n","Date":"18 Mar 1997\n","Location":"Valencia, Spain\n","Notes":"Won Spanish light-middleweight title\n"},{"No":"44\n","Result":"Win\n","Record":"40–4\n","Opponent":"Juan Ramon Medina\n","Type":"TKO\n","Round_Time":"8 (12)\n","Date":"12 Jul 1996\n","Location":"Hernani, Spain\n","Notes":"Won WBC Mundo Hispano light-middleweight title\n"},{"No":"43\n","Result":"Win\n","Record":"39–4\n","Opponent":"Tibor Horvath\n","Type":"TKO\n","Round_Time":"4 (6)\n","Date":"16 May 1996\n","Location":"Madrid, Spain\n","Notes":"\n"},{"No":"42\n","Result":"Win\n","Record":"38–4\n","Opponent":"Stefan Driscu\n","Type":"TKO\n","Round_Time":"2 (8)\n","Date":"7 Mar 1996\n","Location":"Madrid, Spain\n","Notes":"\n"},{"No":"41\n","Result":"Loss\n","Record":"37–4\n","Opponent":"Laurent Boudouani\n","Type":"UD\n","Round_Time":"12\n","Date":"6 Jan 1996\n","Location":"Palais des sports Marcel-Cerdan, Levallois-Perret, France\n","Notes":"For European light-middleweight title\n"},{"No":"40\n","Result":"Win\n","Record":"37–3\n","Opponent":"Carlos Rocha Tomar\n","Type":"DQ\n","Round_Time":"6 (6)\n","Date":"14 Jul 1995\n","Location":"Seville, Spain\n","Notes":"\n"},{"No":"39\n","Result":"Loss\n","Record":"36–3\n","Opponent":"Laurent Boudouani\n","Type":"TKO\n","Round_Time":"9 (12)\n","Date":"3 Jan 1995\n","Location":"Épernay, France\n","Notes":"Lost European light-middleweight title\n"},{"No":"38\n","Result":"Win\n","Record":"36–2\n","Opponent":"Ludovic Proto\n","Type":"TKO\n","Round_Time":"8 (12)\n","Date":"23 Jul 1994\n","Location":"Boiro, Spain\n","Notes":"Retained European light-middleweight title\n"},{"No":"37\n","Result":"Win\n","Record":"35–2\n","Opponent":"Patrick Vungbo\n","Type":"PTS\n","Round_Time":"12\n","Date":"29 May 1994\n","Location":"Leganés, Spain\n","Notes":"Retained European light-middleweight title\n"},{"No":"36\n","Result":"Win\n","Record":"34–2\n","Opponent":"Valentino Manca\n","Type":"TKO\n","Round_Time":"3 (12)\n","Date":"25 Mar 1994\n","Location":"Córdoba, Spain\n","Notes":"Retained European light-middleweight title\n"},{"No":"35\n","Result":"Win\n","Record":"33–2\n","Opponent":"Santo Colombo\n","Type":"TKO\n","Round_Time":"3 (12)\n","Date":"19 Feb 1994\n","Location":"Leganés, Spain\n","Notes":"Retained European light-middleweight title\n"},{"No":"34\n","Result":"Win\n","Record":"32–2\n","Opponent":"Bernard Razzano\n","Type":"RTD\n","Round_Time":"6 (12)\n","Date":"11 Jan 1994\n","Location":"Dijon, France\n","Notes":"Won European light-middleweight title\n"},{"No":"33\n","Result":"Win\n","Record":"31–2\n","Opponent":"Hugo Daniel Sclarandi\n","Type":"KO\n","Round_Time":"5 (12)\n","Date":"29 Oct 1993\n","Location":"Leganés, Spain\n","Notes":"Retained WBC Mundo Hispano light-middleweight title\n"},{"No":"32\n","Result":"Win\n","Record":"30–2\n","Opponent":"Javier Rivera\n","Type":"TKO\n","Round_Time":"4 (8)\n","Date":"25 Jun 1993\n","Location":"Leganés, Spain\n","Notes":"\n"},{"No":"31\n","Result":"Loss\n","Record":"29–2\n","Opponent":"Julio César Vásquez\n","Type":"UD\n","Round_Time":"12\n","Date":"24 Apr 1993\n","Location":"Polideportivo Parquesur Sport, Leganés, Spain\n","Notes":"For WBA light-middleweight title\n"},{"No":"30\n","Result":"Win\n","Record":"29–1\n","Opponent":"Jesus Carlos Velez\n","Type":"PTS\n","Round_Time":"8\n","Date":"26 Mar 1993\n","Location":"Leganés, Spain\n","Notes":"\n"},{"No":"29\n","Result":"Win\n","Record":"27–1\n","Opponent":"Enrique Areco\n","Type":"UD\n","Round_Time":"12\n","Date":"12 Dec 1992\n","Location":"Palacio Municipal de Deportes, Oviedo, Spain\n","Notes":"Won vacant WBC Mundo Hispano light-middleweight title\n"},{"No":"28\n","Result":"Win\n","Record":"27–1\n","Opponent":"Antonio Campbell\n","Type":"KO\n","Round_Time":"3 (8)\n","Date":"13 Oct 1992\n","Location":"Leganés, Spain\n","Notes":"\n"},{"No":"27\n","Result":"Win\n","Record":"26–1\n","Opponent":"Vasile Citea\n","Type":"PTS\n","Round_Time":"8\n","Date":"17 Jul 1992\n","Location":"Leganés, Spain\n","Notes":"\n"},{"No":"26\n","Result":"Win\n","Record":"25–1\n","Opponent":"Jorge Sclarandi\n","Type":"UD\n","Round_Time":"8\n","Date":"19 Jun 1992\n","Location":"Leganés, Spain\n","Notes":"\n"},{"No":"25\n","Result":"Win\n","Record":"24–1\n","Opponent":"Saoul Mamby\n","Type":"PTS\n","Round_Time":"8\n","Date":"15 May 1992\n","Location":"Bilbao, Spain\n","Notes":"\n"},{"No":"24\n","Result":"Win\n","Record":"23–1\n","Opponent":"Harry Arroyo\n","Type":"TKO\n","Round_Time":"3 (8)\n","Date":"10 Apr 1992\n","Location":"Leganés, Spain\n","Notes":"\n"},{"No":"23\n","Result":"Win\n","Record":"22–1\n","Opponent":"Edison Martinez\n","Type":"KO\n","Round_Time":"3 (8)\n","Date":"14 Mar 1992\n","Location":"Leganés, Spain\n","Notes":"\n"},{"No":"22\n","Result":"Win\n","Record":"21–1\n","Opponent":"Lindon Scarlett\n","Type":"PTS\n","Round_Time":"8\n","Date":"8 Feb 1992\n","Location":"Polideportivo Parquesur Sport, Leganés, Spain\n","Notes":"\n"},{"No":"21\n","Result":"Win\n","Record":"20–1\n","Opponent":"Gejza Stipak\n","Type":"RTD\n","Round_Time":"4 (8), 3:00\n","Date":"17 Jan 1992\n","Location":"Leganés, Spain\n","Notes":"\n"},{"No":"20\n","Result":"Win\n","Record":"19–1\n","Opponent":"Patrick Vungbo\n","Type":"TKO\n","Round_Time":"5 (8)\n","Date":"6 Dec 1991\n","Location":"Leganés, Spain\n","Notes":"\n"},{"No":"19\n","Result":"Win\n","Record":"18–1\n","Opponent":"Domingo Sanchez\n","Type":"TKO\n","Round_Time":"4 (10)\n","Date":"5 Jul 1991\n","Location":"Lugo, Spain\n","Notes":"Retained Spanish welterweight title\n"},{"No":"18\n","Result":"Win\n","Record":"17–1\n","Opponent":"Juan Rosario\n","Type":"TKO\n","Round_Time":"6 (8)\n","Date":"18 May 1991\n","Location":"Madrid, Spain\n","Notes":"\n"},{"No":"17\n","Result":"Win\n","Record":"16–1\n","Opponent":"Eric Dindaine\n","Type":"PTS\n","Round_Time":"8\n","Date":"21 Dec 1990\n","Location":"Leganés, Spain\n","Notes":"\n"},{"No":"16\n","Result":"Win\n","Record":"15–1\n","Opponent":"Alfonso Redondo\n","Type":"TKO\n","Round_Time":"4 (10)\n","Date":"19 Oct 1990\n","Location":"Leganés, Spain\n","Notes":"Won Spanish welterweight title\n"},{"No":"15\n","Result":"Win\n","Record":"14–1\n","Opponent":"Jose Salinas\n","Type":"KO\n","Round_Time":"1 (8)\n","Date":"17 Aug 1990\n","Location":"Almería, Spain\n","Notes":"\n"},{"No":"14\n","Result":"Win\n","Record":"13–1\n","Opponent":"Claudio Salgado\n","Type":"TKO\n","Round_Time":"1 (6)\n","Date":"14 Jul 1990\n","Location":"Parla, Spain\n","Notes":"\n"},{"No":"13\n","Result":"Win\n","Record":"12–1\n","Opponent":"Mateo Valdez\n","Type":"TKO\n","Round_Time":"2 (8)\n","Date":"31 May 1990\n","Location":"Madrid, Spain\n","Notes":"\n"},{"No":"12\n","Result":"Win\n","Record":"11–1\n","Opponent":"Felix Rodriguez\n","Type":"TKO\n","Round_Time":"5 (8)\n","Date":"5 May 1990\n","Location":"Zaragoza, Spain\n","Notes":"\n"},{"No":"11\n","Result":"Win\n","Record":"10–1\n","Opponent":"Carlos Tavarez\n","Type":"TKO\n","Round_Time":"2 (6)\n","Date":"16 Feb 1990\n","Location":"Bilbao, Spain\n","Notes":"\n"},{"No":"10\n","Result":"Win\n","Record":"9–1\n","Opponent":"Louie Antuna\n","Type":"PTS\n","Round_Time":"6\n","Date":"30 Dec 1989\n","Location":"Santoña, Spain\n","Notes":"\n"},{"No":"9\n","Result":"Win\n","Record":"8–1\n","Opponent":"Jimmy Bartes\n","Type":"TKO\n","Round_Time":"2 (6)\n","Date":"16 Nov 1989\n","Location":"Madrid, Spain\n","Notes":"\n"},{"No":"8\n","Result":"Loss\n","Record":"7–1\n","Opponent":"Del Bryan\n","Type":"PTS\n","Round_Time":"8\n","Date":"19 Aug 1989\n","Location":"Benidorm, Spain\n","Notes":"\n"},{"No":"7\n","Result":"Win\n","Record":"7–0\n","Opponent":"Victor Carvalho\n","Type":"PTS\n","Round_Time":"6\n","Date":"29 Jul 1989\n","Location":"Madrid, Spain\n","Notes":"\n"},{"No":"6\n","Result":"Win\n","Record":"6–0\n","Opponent":"Juan Antonio Lopez\n","Type":"PTS\n","Round_Time":"8\n","Date":"14 Jun 1989\n","Location":"Palacio de Deportes, Madrid, Spain\n","Notes":"\n"},{"No":"5\n","Result":"Win\n","Record":"5–0\n","Opponent":"Modesto Villardell\n","Type":"TKO\n","Round_Time":"1 (6)\n","Date":"23 Feb 1989\n","Location":"Madrid, Spain\n","Notes":"\n"},{"No":"4\n","Result":"Win\n","Record":"4–0\n","Opponent":"Santiago Vasquez\n","Type":"PTS\n","Round_Time":"6\n","Date":"19 Nov 1988\n","Location":"Irun, Spain\n","Notes":"\n"},{"No":"3\n","Result":"Win\n","Record":"3–0\n","Opponent":"Juan Perez\n","Type":"TKO\n","Round_Time":"1 (4)\n","Date":"4 Nov 1988\n","Location":"Torrejón de Ardoz, Spain\n","Notes":"\n"},{"No":"2\n","Result":"Win\n","Record":"2–0\n","Opponent":"Angel Diez\n","Type":"TKO\n","Round_Time":"4 (6)\n","Date":"2 Sep 1988\n","Location":"San Martín de Valdeiglesias, Spain\n","Notes":"\n"},{"No":"1\n","Result":"Win\n","Record":"1–0\n","Opponent":"Angel Diez\n","Type":"PTS\n","Round_Time":"6\n","Date":"22 Jul 1988\n","Location":"Madrid, Spain\n","Notes":"\n"}]}